LICENSE
MANIFEST.in
README
ez_setup.py
setup.py
django_pollngo.egg-info/PKG-INFO
django_pollngo.egg-info/SOURCES.txt
django_pollngo.egg-info/dependency_links.txt
django_pollngo.egg-info/not-zip-safe
django_pollngo.egg-info/top_level.txt
pollngo/__init__.py
pollngo/admin.py
pollngo/models.py
pollngo/pforms.py
pollngo/pygooglechart.py
pollngo/urls.py
pollngo/views.py
pollngo/templates/pollngo/base.html
pollngo/templates/pollngo/create.html
pollngo/templates/pollngo/help.html
pollngo/templates/pollngo/index.html
pollngo/templates/pollngo/question.html
pollngo/templates/pollngo/results.html
project/__init__.py
project/localsettings.py
project/manage.py
project/settings.py
project/urls.py
project/pollngo/__init__.py
project/pollngo/admin.py
project/pollngo/models.py
project/pollngo/pforms.py
project/pollngo/pygooglechart.py
project/pollngo/urls.py
project/pollngo/views.py